semantic_sense/__init__.py
semantic_sense/core.py
semantic_sense/model_loader.py
semantic_sense/utils.py
semantic_sense/models/all-MiniLM-L6-v2/config.json
semantic_sense/models/all-MiniLM-L6-v2/modules.json
semantic_sense/models/all-MiniLM-L6-v2/pytorch_model.bin
semantic_sense/models/all-MiniLM-L6-v2/special_tokens_map.json
semantic_sense/models/all-MiniLM-L6-v2/tokenizer.json
semantic_sense/models/all-MiniLM-L6-v2/tokenizer_config.json
semantic_sense/models/all-MiniLM-L6-v2/vocab.txt
semantic_sense/models/all-MiniLM-L6-v2/1_Pooling/config.json
semantic_sense-0.1.1.dist-info/licenses/LICENSE
semantic_sense-0.1.1.dist-info/METADATA
semantic_sense-0.1.1.dist-info/WHEEL
semantic_sense-0.1.1.dist-info/top_level.txt
semantic_sense-0.1.1.dist-info/RECORD
