Metadata-Version: 2.4
Name: semantic_sense
Version: 0.1.1
Summary: Hybrid semantic anomaly detector: row text embeddings + scaled numeric features.
Author-email: Rezuanur Rahman Dip <rezuanur99@gmail.com>
License: Copyright 2025 Rezuanur Rahman Dip
Requires-Python: >=3.8
License-File: LICENSE
Requires-Dist: pandas>=1.5
Requires-Dist: numpy>=1.23
Requires-Dist: scikit-learn>=1.2
Requires-Dist: sentence-transformers>=2.2
Dynamic: license-file
